ckeditor/__init__.py
ckeditor/apps.py
ckeditor/configs.py
ckeditor/fields.py
ckeditor/widgets.py
ckeditor/static/ckeditor/ckeditor-init.js
ckeditor/static/ckeditor/ckeditor.css
ckeditor/static/ckeditor/ckeditor/CHANGES.md
ckeditor/static/ckeditor/ckeditor/LICENSE.md
ckeditor/static/ckeditor/ckeditor/README.md
ckeditor/static/ckeditor/ckeditor/SECURITY.md
ckeditor/static/ckeditor/ckeditor/bender-runner.config.json
ckeditor/static/ckeditor/ckeditor/build-config.js
ckeditor/static/ckeditor/ckeditor/ckeditor.js
ckeditor/static/ckeditor/ckeditor/config.js
ckeditor/static/ckeditor/ckeditor/contents.css
ckeditor/static/ckeditor/ckeditor/styles.js
ckeditor/static/ckeditor/ckeditor/adapters/jquery.js
ckeditor/static/ckeditor/ckeditor/lang/af.js
ckeditor/static/ckeditor/ckeditor/lang/ar.js
ckeditor/static/ckeditor/ckeditor/lang/az.js
ckeditor/static/ckeditor/ckeditor/lang/bg.js
ckeditor/static/ckeditor/ckeditor/lang/bn.js
ckeditor/static/ckeditor/ckeditor/lang/bs.js
ckeditor/static/ckeditor/ckeditor/lang/ca.js
ckeditor/static/ckeditor/ckeditor/lang/cs.js
ckeditor/static/ckeditor/ckeditor/lang/cy.js
ckeditor/static/ckeditor/ckeditor/lang/da.js
ckeditor/static/ckeditor/ckeditor/lang/de-ch.js
ckeditor/static/ckeditor/ckeditor/lang/de.js
ckeditor/static/ckeditor/ckeditor/lang/el.js
ckeditor/static/ckeditor/ckeditor/lang/en-au.js
ckeditor/static/ckeditor/ckeditor/lang/en-ca.js
ckeditor/static/ckeditor/ckeditor/lang/en-gb.js
ckeditor/static/ckeditor/ckeditor/lang/en.js
ckeditor/static/ckeditor/ckeditor/lang/eo.js
ckeditor/static/ckeditor/ckeditor/lang/es-mx.js
ckeditor/static/ckeditor/ckeditor/lang/es.js
ckeditor/static/ckeditor/ckeditor/lang/et.js
ckeditor/static/ckeditor/ckeditor/lang/eu.js
ckeditor/static/ckeditor/ckeditor/lang/fa.js
ckeditor/static/ckeditor/ckeditor/lang/fi.js
ckeditor/static/ckeditor/ckeditor/lang/fo.js
ckeditor/static/ckeditor/ckeditor/lang/fr-ca.js
ckeditor/static/ckeditor/ckeditor/lang/fr.js
ckeditor/static/ckeditor/ckeditor/lang/gl.js
django_ckeditor_by_toc-1.0.dist-info/LICENSE
django_ckeditor_by_toc-1.0.dist-info/METADATA
django_ckeditor_by_toc-1.0.dist-info/WHEEL
django_ckeditor_by_toc-1.0.dist-info/top_level.txt
django_ckeditor_by_toc-1.0.dist-info/RECORD
